{
  "Aether Channeler": [
    "removal",
    "creature-removal",
    "artifact-removal",
    "enchantment-removal",
    "planeswalker-removal"
  ],
  "Archangel of Wrath": [
    "removal",
    "creature-removal",
    "planeswalker-removal"
  ],
  "Artillery Blast": [
    "removal",
    "creature-removal"
  ],
  "Balduvian Berserker": [
    "removal",
    "creature-removal",
    "planeswalker-removal"
  ],
  "Benalish Sleeper": [
    "removal",
    "creature-removal"
  ],
  "Bite Down": [
    "removal",
    "creature-removal",
    "planeswalker-removal"
  ],
  "Bone Splinters": [
    "removal",
    "creature-removal"
  ],
  "Braids's Frightful Return": [
    "removal",
    "creature-removal",
    "artifact-removal",
    "enchantment-removal",
    "planeswalker-removal"
  ],
  "Braids, Arisen Nightmare": [
    "removal"
  ],
  "Broken Wings": [
    "removal",
    "creature-removal",
    "artifact-removal",
    "enchantment-removal"
  ],
  "Chaotic Transformation": [
    "removal",
    "creature-removal",
    "artifact-removal",
    "enchantment-removal",
    "planeswalker-removal"
  ],
  "Choking Miasma": [
    "removal",
    "creature-removal"
  ],
  "Citizen's Arrest": [
    "removal",
    "creature-removal",
    "planeswalker-removal"
  ],
  "Cleaving Skyrider": [
    "removal",
    "creature-removal",
    "planeswalker-removal"
  ],
  "Cut Down": [
    "removal",
    "creature-removal"
  ],
  "Defiler of Instinct": [
    "removal",
    "creature-removal",
    "planeswalker-removal"
  ],
  "Destroy Evil": [
    "removal",
    "creature-removal",
    "enchantment-removal"
  ],
  "Drag to the Bottom": [
    "removal",
    "creature-removal"
  ],
  "Ertai Resurrected": [
    "removal",
    "creature-removal",
    "planeswalker-removal"
  ],
  "Extinguish the Light": [
    "removal",
    "creature-removal",
    "planeswalker-removal"
  ],
  "Fires of Victory": [
    "removal",
    "creature-removal",
    "planeswalker-removal"
  ],
  "Flowstone Infusion": [
    "removal",
    "creature-removal"
  ],
  "Ghitu Amplifier": [
    "removal",
    "creature-removal"
  ],
  "Hurler Cyclops": [
    "removal",
    "creature-removal",
    "planeswalker-removal"
  ],
  "Hurloon Battle Hymn": [
    "removal",
    "creature-removal",
    "planeswalker-removal"
  ],
  "In Thrall to the Pit": [
    "removal",
    "creature-removal"
  ],
  "Jaya's Firenado": [
    "removal",
    "creature-removal",
    "planeswalker-removal"
  ],
  "Jaya, Fiery Negotiator": [
    "removal",
    "creature-removal"
  ],
  "Karn's Sylex": [
    "removal",
    "creature-removal",
    "artifact-removal",
    "enchantment-removal",
    "planeswalker-removal"
  ],
  "Karn, Living Legacy": [
    "removal",
    "creature-removal",
    "planeswalker-removal"
  ],
  "Leyline Binding": [
    "removal",
    "creature-removal",
    "artifact-removal",
    "enchantment-removal",
    "planeswalker-removal"
  ],
  "Lightning Strike": [
    "removal",
    "creature-removal",
    "planeswalker-removal"
  ],
  "Liliana of the Veil": [
    "removal",
    "creature-removal",
    "artifact-removal",
    "enchantment-removal",
    "planeswalker-removal"
  ],
  "Meteorite": [
    "removal",
    "creature-removal",
    "planeswalker-removal"
  ],
  "Prayer of Binding": [
    "removal",
    "creature-removal",
    "artifact-removal",
    "enchantment-removal",
    "planeswalker-removal"
  ],
  "Rona's Vortex": [
    "removal",
    "creature-removal",
    "planeswalker-removal"
  ],
  "Runic Shot": [
    "removal",
    "creature-removal"
  ],
  "Silverback Elder": [
    "removal",
    "artifact-removal",
    "enchantment-removal"
  ],
  "Smash to Dust": [
    "removal",
    "creature-removal",
    "artifact-removal"
  ],
  "Sol'Kanar the Tainted": [
    "removal",
    "creature-removal",
    "planeswalker-removal"
  ],
  "Splatter Goblin": [
    "removal",
    "creature-removal"
  ],
  "Tail Swipe": [
    "removal",
    "creature-removal"
  ],
  "Tear Asunder": [
    "removal",
    "creature-removal",
    "artifact-removal",
    "enchantment-removal",
    "planeswalker-removal"
  ],
  "Temporal Firestorm": [
    "removal",
    "creature-removal",
    "planeswalker-removal"
  ],
  "Temporary Lockdown": [
    "removal",
    "creature-removal",
    "artifact-removal",
    "enchantment-removal",
    "planeswalker-removal"
  ],
  "The Elder Dragon War": [
    "removal",
    "creature-removal"
  ],
  "The Phasing of Zhalfir": [
    "removal",
    "creature-removal"
  ],
  "Tolarian Geyser": [
    "removal",
    "creature-removal"
  ],
  "Tribute to Urborg": [
    "removal",
    "creature-removal"
  ],
  "Yavimaya Steelcrusher": [
    "removal",
    "artifact-removal"
  ],
  "Yotia Declares War": [
    "removal",
    "creature-removal",
    "planeswalker-removal"
  ]
}
